django_jwt_middleware/__init__.py
django_jwt_middleware/source.py
django_jwt_middleware-1.1.3.dist-info/LICENSE
django_jwt_middleware-1.1.3.dist-info/METADATA
django_jwt_middleware-1.1.3.dist-info/WHEEL
django_jwt_middleware-1.1.3.dist-info/top_level.txt
django_jwt_middleware-1.1.3.dist-info/RECORD
