Metadata-Version: 2.1
Name: django_jwt_middleware
Version: 1.1.3
Summary: Authorize request with JSON Web Tokens
Home-page: https://github.com/rizki4106/django_jwt_middleware
Author: Rizki
Author-email: rizkimaulana348@gmail.com
License: UNKNOWN
Project-URL: Bug Tracker, https://github.com/rizki4106/django_jwt_middleware/issues
Platform: UNKNOWN
Classifier: Programming Language :: Python :: 3
Classifier: License :: OSI Approved :: MIT License
Classifier: Operating System :: OS Independent
Requires-Python: >=3.6
License-File: LICENSE
